{
  "indicator": "AG.CON.FERT.ZS",
  "indicator_name": "Fertilizer consumption (kilograms per hectare of arable land)",
  "data": [
    {
      "year": 2010,
      "value": 149.405034324943,
      "indicator": "AG.CON.FERT.ZS",
      "indicator_name": "Fertilizer consumption (kilograms per hectare of arable land)",
      "country": "West Bank and Gaza",
      "source": "worldbank"
    },
    {
      "year": 2011,
      "value": 162.807100035265,
      "indicator": "AG.CON.FERT.ZS",
      "indicator_name": "Fertilizer consumption (kilograms per hectare of arable land)",
      "country": "West Bank and Gaza",
      "source": "worldbank"
    },
    {
      "year": 2012,
      "value": 182.068348294847,
      "indicator": "AG.CON.FERT.ZS",
      "indicator_name": "Fertilizer consumption (kilograms per hectare of arable land)",
      "country": "West Bank and Gaza",
      "source": "worldbank"
    },
    {
      "year": 2013,
      "value": 165.852122494891,
      "indicator": "AG.CON.FERT.ZS",
      "indicator_name": "Fertilizer consumption (kilograms per hectare of arable land)",
      "country": "West Bank and Gaza",
      "source": "worldbank"
    },
    {
      "year": 2014,
      "value": 160.22066924002,
      "indicator": "AG.CON.FERT.ZS",
      "indicator_name": "Fertilizer consumption (kilograms per hectare of arable land)",
      "country": "West Bank and Gaza",
      "source": "worldbank"
    },
    {
      "year": 2015,
      "value": 181.407913887522,
      "indicator": "AG.CON.FERT.ZS",
      "indicator_name": "Fertilizer consumption (kilograms per hectare of arable land)",
      "country": "West Bank and Gaza",
      "source": "worldbank"
    },
    {
      "year": 2016,
      "value": 230.750005991284,
      "indicator": "AG.CON.FERT.ZS",
      "indicator_name": "Fertilizer consumption (kilograms per hectare of arable land)",
      "country": "West Bank and Gaza",
      "source": "worldbank"
    },
    {
      "year": 2017,
      "value": 215.87024136956,
      "indicator": "AG.CON.FERT.ZS",
      "indicator_name": "Fertilizer consumption (kilograms per hectare of arable land)",
      "country": "West Bank and Gaza",
      "source": "worldbank"
    },
    {
      "year": 2018,
      "value": 205.227763768882,
      "indicator": "AG.CON.FERT.ZS",
      "indicator_name": "Fertilizer consumption (kilograms per hectare of arable land)",
      "country": "West Bank and Gaza",
      "source": "worldbank"
    },
    {
      "year": 2019,
      "value": 234.673175743072,
      "indicator": "AG.CON.FERT.ZS",
      "indicator_name": "Fertilizer consumption (kilograms per hectare of arable land)",
      "country": "West Bank and Gaza",
      "source": "worldbank"
    },
    {
      "year": 2020,
      "value": 262.999419456022,
      "indicator": "AG.CON.FERT.ZS",
      "indicator_name": "Fertilizer consumption (kilograms per hectare of arable land)",
      "country": "West Bank and Gaza",
      "source": "worldbank"
    },
    {
      "year": 2021,
      "value": 216.109785202864,
      "indicator": "AG.CON.FERT.ZS",
      "indicator_name": "Fertilizer consumption (kilograms per hectare of arable land)",
      "country": "West Bank and Gaza",
      "source": "worldbank"
    },
    {
      "year": 2022,
      "value": 199.522673031026,
      "indicator": "AG.CON.FERT.ZS",
      "indicator_name": "Fertilizer consumption (kilograms per hectare of arable land)",
      "country": "West Bank and Gaza",
      "source": "worldbank"
    },
    {
      "year": 2023,
      "value": 199.522673031026,
      "indicator": "AG.CON.FERT.ZS",
      "indicator_name": "Fertilizer consumption (kilograms per hectare of arable land)",
      "country": "West Bank and Gaza",
      "source": "worldbank"
    }
  ],
  "metadata": {
    "source": "World Bank Open Data",
    "last_updated": "2025-10-29T21:01:54.694Z",
    "total_points": 14
  },
  "validation": {
    "qualityScore": 1,
    "completeness": 1,
    "consistency": 1,
    "accuracy": 1,
    "meetsThreshold": true,
    "errorCount": 0,
    "warningCount": 0
  }
}